sublate.py
sublate-0.3.1.dist-info/entry_points.txt
sublate-0.3.1.dist-info/LICENSE
sublate-0.3.1.dist-info/WHEEL
sublate-0.3.1.dist-info/METADATA
sublate-0.3.1.dist-info/RECORD
