Metadata-Version: 2.1
Name: sublate
Version: 0.3.1
Summary: A high-level toolkit.
Author: Jonathan Esposito
Author-email: jonathan@esposito.page
Requires-Python: >=3.7,<4.0
Classifier: Programming Language :: Python :: 3
Classifier: Programming Language :: Python :: 3.7
Classifier: Programming Language :: Python :: 3.8
Classifier: Programming Language :: Python :: 3.9
Classifier: Programming Language :: Python :: 3.10
Classifier: Programming Language :: Python :: 3.11
Requires-Dist: jinja2 (>=3.1.2,<4.0.0)
Requires-Dist: pyyaml (>=6.0,<7.0)
